nyptune/__init__.py
nyptune/cache.py
nyptune/cli.py
nyptune/jupyter.py
nyptune/magic.py
nyptune/util.py
nyptune/directory/__init__.py
nyptune/directory/base.py
nyptune/directory/encrypted.py
nyptune/directory/local.py
nyptune/handler/__init__.py
nyptune/handler/base.py
nyptune/handler/download.py
nyptune/handler/handler_base.py
nyptune/handler/np.py
nyptune/handler/path.py
nyptune/handler/pickle.py
nyptune-0.0.1.1528068397.dist-info/entry_points.txt
nyptune-0.0.1.1528068397.dist-info/WHEEL
nyptune-0.0.1.1528068397.dist-info/METADATA
nyptune-0.0.1.1528068397.dist-info/RECORD
